README.md
setup.py
clusterone/__init__.py
clusterone/auth.py
clusterone/client_exceptions.py
clusterone/clusterone_cli.py
clusterone/instances.py
clusterone/messages.py
clusterone/test_exceptions.py
clusterone/test_main.py
clusterone/test_programatic.py
clusterone/test_responses.py
clusterone/test_schema.py
clusterone/utils.py
clusterone/version.py
clusterone.egg-info/PKG-INFO
clusterone.egg-info/SOURCES.txt
clusterone.egg-info/dependency_links.txt
clusterone.egg-info/entry_points.txt
clusterone.egg-info/requires.txt
clusterone.egg-info/top_level.txt
clusterone/business_logic/__init__.py
clusterone/business_logic/command.py
clusterone/business_logic/dataset_commands.py
clusterone/business_logic/generic_commands.py
clusterone/business_logic/job_commands.py
clusterone/business_logic/notebook_commands.py
clusterone/business_logic/providers.py
clusterone/commands/__init__.py
clusterone/commands/config/__init__.py
clusterone/commands/config/cmd.py
clusterone/commands/config/test_cmd.py
clusterone/commands/create/__init__.py
clusterone/commands/create/dataset/__init__.py
clusterone/commands/create/dataset/cmd.py
clusterone/commands/create/dataset/test_cmd.py
clusterone/commands/create/job/__init__.py
clusterone/commands/create/job/base_cmd.py
clusterone/commands/create/job/distributed.py
clusterone/commands/create/job/single.py
clusterone/commands/create/job/test_base_cmd.py
clusterone/commands/create/notebook/__init__.py
clusterone/commands/create/notebook/cmd.py
clusterone/commands/create/notebook/test_notebook.py
clusterone/commands/create/project/__init__.py
clusterone/commands/create/project/cmd.py
clusterone/commands/create/project/helper.py
clusterone/commands/create/project/test_cmd.py
clusterone/commands/create/project/test_helper.py
clusterone/commands/download/__init__.py
clusterone/commands/download/job/__init__.py
clusterone/commands/download/job/cmd.py
clusterone/commands/get/__init__.py
clusterone/commands/get/dataset/__init__.py
clusterone/commands/get/dataset/cmd.py
clusterone/commands/get/dataset/test_cmd.py
clusterone/commands/get/events/__init__.py
clusterone/commands/get/events/cmd.py
clusterone/commands/get/events/test_cmd.py
