Metadata-Version: 1.2
Name: clusterone
Version: 0.15.2
Summary: Clusterone CLI and Python library.
Home-page: https://clusterone.com
Author: Clusterone
Author-email: info@clusterone.com
License: MIT
Platform: UNKNOWN
Requires-Python: >2.6, !=3.0.*, !=3.1.*, !=3.2.*, !=3.3.*, !=3.4.*, <4
